meta_learning_framework/__init__.py
meta_learning_framework/exceptions.py
meta_learning_framework/types.py
meta_learning_framework/base_model/__init__.py
meta_learning_framework/base_model/base_model.py
meta_learning_framework/meta/__init__.py
meta_learning_framework/meta/meta_classifier.py
meta_learning_framework/meta/meta_learning_ensemble.py
meta_learning_framework/naive_ensemble/__init__.py
meta_learning_framework/naive_ensemble/naive_ensemble.py
meta_learning_framework/utils/__init__.py
meta_learning_framework/utils/combiner.py
meta_learning_framework/utils/error_measurer.py
meta_learning_framework/utils/selector.py
tests/__init__.py
meta_learning_framework-0.1.0.dist-info/LICENSE
meta_learning_framework-0.1.0.dist-info/METADATA
meta_learning_framework-0.1.0.dist-info/WHEEL
meta_learning_framework-0.1.0.dist-info/top_level.txt
meta_learning_framework-0.1.0.dist-info/RECORD
