Metadata-Version: 2.1
Name: meta-learning-framework
Version: 0.1.0
Summary: A framework to apply a meta learning algorithm at instance level (learn how to ensemble models).
Home-page: https://github.com/CaioUeno/meta-learning-framework/
Author: Caio Ueno
Author-email: caiol.ueno@gmail.com
Classifier: Programming Language :: Python :: 3
Classifier: License :: OSI Approved :: MIT License
Classifier: Operating System :: OS Independent
Requires-Python: >=3.7
License-File: LICENSE
